web/__init__.py
web/controller.py
web/main.py
web/manifest.py
web/model.py
web/setting.py
web/ui.py
web/vultr.py
web/static/bootstrap/dist/css/bootstrap-theme.css
web/static/bootstrap/dist/css/bootstrap-theme.css.map
web/static/bootstrap/dist/css/bootstrap-theme.min.css
web/static/bootstrap/dist/css/bootstrap.css
web/static/bootstrap/dist/css/bootstrap.css.map
web/static/bootstrap/dist/css/bootstrap.min.css
web/static/bootstrap/dist/fonts/glyphicons-halflings-regular.eot
web/static/bootstrap/dist/fonts/glyphicons-halflings-regular.svg
web/static/bootstrap/dist/fonts/glyphicons-halflings-regular.ttf
web/static/bootstrap/dist/fonts/glyphicons-halflings-regular.woff
web/static/bootstrap/dist/fonts/glyphicons-halflings-regular.woff2
web/static/bootstrap/dist/js/bootstrap.js
web/static/bootstrap/dist/js/bootstrap.min.js
web/static/bootstrap/grunt/bs-glyphicons-data-generator.js
web/static/bootstrap/grunt/bs-lessdoc-parser.js
web/static/bootstrap/grunt/bs-raw-files-generator.js
web/static/bootstrap/grunt/sauce_browsers.yml
web/static/bootstrap/js/affix.js
web/static/bootstrap/js/alert.js
web/static/bootstrap/js/button.js
web/static/bootstrap/js/carousel.js
web/static/bootstrap/js/collapse.js
web/static/bootstrap/js/dropdown.js
web/static/bootstrap/js/modal.js
web/static/bootstrap/js/popover.js
web/static/bootstrap/js/scrollspy.js
web/static/bootstrap/js/tab.js
web/static/bootstrap/js/tooltip.js
web/static/bootstrap/js/transition.js
web/static/bootstrap/less/alerts.less
web/static/bootstrap/less/badges.less
web/static/bootstrap/less/bootstrap.less
web/static/bootstrap/less/breadcrumbs.less
web/static/bootstrap/less/button-groups.less
web/static/bootstrap/less/buttons.less
web/static/bootstrap/less/carousel.less
web/static/bootstrap/less/close.less
web/static/bootstrap/less/code.less
web/static/bootstrap/less/component-animations.less
web/static/bootstrap/less/dropdowns.less
web/static/bootstrap/less/forms.less
x_mroy_1047-0.2.0.dist-info/DESCRIPTION.rst
x_mroy_1047-0.2.0.dist-info/METADATA
x_mroy_1047-0.2.0.dist-info/RECORD
x_mroy_1047-0.2.0.dist-info/WHEEL
x_mroy_1047-0.2.0.dist-info/entry_points.txt
x_mroy_1047-0.2.0.dist-info/metadata.json
x_mroy_1047-0.2.0.dist-info/top_level.txt
