Metadata-Version: 2.0
Name: x-mroy-1047
Version: 0.2.0
Summary: a anayzer package
Home-page: https://github.com/Qingluan/.git
Author: Qing luan
Author-email: UNKNOWN
License: MIT
Platform: UNKNOWN
Requires-Dist: mroylib-min (>=1.5.1)
Requires-Dist: geoip2
Requires-Dist: fabric3
Requires-Dist: qrcode
Requires-Dist: pillow
Requires-Dist: image
Requires-Dist: xlwt
Requires-Dist: xlrd
Requires-Dist: x-mroy-1050
Requires-Dist: x-mroy-1045
